ai_design_insights/__init__.py
ai_design_insights/main.py
ai_design_insights/prompts.py
ai_design_insights-2025.12.21145447.dist-info/METADATA
ai_design_insights-2025.12.21145447.dist-info/WHEEL
ai_design_insights-2025.12.21145447.dist-info/top_level.txt
ai_design_insights-2025.12.21145447.dist-info/RECORD
