Metadata-Version: 2.4
Name: ai-design-insights
Version: 2025.12.21145447
Summary: A new package that helps extract and structure insights from discussions about AI system design challenges. Users can input text from forums, articles, or discussions, and the package will use llmatch
Author-email: ai-design-insights <hi@eugene.plus>
License: MIT
Project-URL: Homepage, https://github.com/chigwell/ai-design-insights
Requires-Python: >=3.9
Requires-Dist: langchain-llm7>=0.0.0
Requires-Dist: llmatch-messages>=0.0.0
Requires-Dist: langchain-core>=0.3.0
